Admin_utils/__init__.py
Admin_utils/create_delete_allure_project.py
Admin_utils/custom_logger.py
Admin_utils/custom_logger_formatter.py
Admin_utils/general_utils.py
Admin_utils/gherkin_helper.py
Admin_utils/run_gherkin_lint.py
Admin_utils/send_mail.py
Admin_utils/send_report_to_allure_server.py
Admin_utils/allure_tools/__init__.py
Admin_utils/allure_tools/allure_server_api_client.py
Admin_utils/get_tests_analytics/__init__.py
Admin_utils/get_tests_analytics/all_tags.py
Admin_utils/get_tests_analytics/get_test_cases_collection.py
Admin_utils/get_tests_analytics/diff_test_cases/__init__.py
Admin_utils/get_tests_analytics/diff_test_cases/find_duplicates_of_scenarios_in_tr.py
Admin_utils/get_tests_analytics/diff_test_cases/get_all_ids_cases_from_features.py
Admin_utils/get_tests_analytics/diff_test_cases/get_cases_analytics.py
Admin_utils/get_tests_analytics/diff_test_cases/get_difference_between_tr_and_features.py
Admin_utils/get_tests_analytics/diff_test_cases/get_info_from_regression_run.py
Admin_utils/get_time_from_drone/__init__.py
Admin_utils/get_time_from_drone/calculate_total_runtime.py
Admin_utils/get_time_from_drone/time_logger.py
Admin_utils/helper_constant_data/__init__.py
Admin_utils/helper_constant_data/helper_constants.py
Load_tests/__init__.py
Load_tests/conftest.py
Load_tests/steps_defs.py
Load_tests/base_classes/__init__.py
Load_tests/base_classes/load_test_runner.py
Load_tests/base_classes/load_tests_base_http_user_model.py
Load_tests/base_classes/load_tests_base_test_suite_model.py
Load_tests/test_classes/__init__.py
Load_tests/test_classes/load_tests.py
Load_tests/test_classes/load_tests_mapping.py
Load_tests/test_suites/__init__.py
Load_tests/test_suites/content_on_sale_load_test_suite.py
Load_tests/test_suites/organization_load_test_suite.py
Load_tests/test_suites/sync_and_meta_load_test_suite.py
Load_tests/test_suites/tips_load_test_suite.py
Load_tests/tests/__init__.py
Load_tests/tests/test_load_content_on_sale.py
pytest_testrail_api-1.0.1.dist-info/METADATA
pytest_testrail_api-1.0.1.dist-info/WHEEL
pytest_testrail_api-1.0.1.dist-info/entry_points.txt
pytest_testrail_api-1.0.1.dist-info/top_level.txt
pytest_testrail_api-1.0.1.dist-info/RECORD
