Metadata-Version: 2.1
Name: pytest-testrail-api
Version: 1.0.1
Summary: TestRail Api Python Client
Home-page: UNKNOWN
Author: Yevhen Halitsyn
Author-email: halitsyny@science.regn.net
License: UNKNOWN
Platform: UNKNOWN
Requires-Dist: requests
Requires-Dist: pytest
Requires-Dist: gherkin-official >=4.1.0
Requires-Dist: pytest-bdd >=3.3.0
Requires-Dist: typing
